cortexa_sdk/__init__.py
cortexa_sdk/cli.py
cortexa_sdk_duan-0.1.0.dist-info/METADATA
cortexa_sdk_duan-0.1.0.dist-info/WHEEL
cortexa_sdk_duan-0.1.0.dist-info/entry_points.txt
cortexa_sdk_duan-0.1.0.dist-info/top_level.txt
cortexa_sdk_duan-0.1.0.dist-info/RECORD
