Metadata-Version: 2.4
Name: cortexa-sdk-duan
Version: 0.1.0
Summary: User-side Python SDK for downloading datasets and assets from Cortexa. Now use 'annotation_type' parameter (rect, polygon) for YOLO.
Author: Cortexa
Project-URL: Homepage, https://example.com
Requires-Python: >=3.8
Requires-Dist: requests
